LICENCE
MANIFEST.in
README.rst
setup.py
django_initial_avatars.egg-info/PKG-INFO
django_initial_avatars.egg-info/SOURCES.txt
django_initial_avatars.egg-info/dependency_links.txt
django_initial_avatars.egg-info/not-zip-safe
django_initial_avatars.egg-info/requires.txt
django_initial_avatars.egg-info/top_level.txt
initial_avatars/__init__.py
initial_avatars/compat.py
initial_avatars/generator.py
initial_avatars/models.py
initial_avatars/urls.py
initial_avatars/utils.py
initial_avatars/views.py
initial_avatars/font/UbuntuMono-B.ttf
initial_avatars/migrations/0001_initial.py
initial_avatars/migrations/0002_delete_avatar_with_user.py
initial_avatars/migrations/__init__.py
initial_avatars/templatetags/__init__.py
initial_avatars/templatetags/initialavatar.py